pysmee/__init__.py
pysmee/pysmee.py
pysmee-0.1.1.dist-info/METADATA
pysmee-0.1.1.dist-info/RECORD
pysmee-0.1.1.dist-info/WHEEL
pysmee-0.1.1.dist-info/entry_points.txt
pysmee-0.1.1.dist-info/top_level.txt
